costs_benefits_ssp/__init__.py
costs_benefits_ssp/cb_calculate.py
costs_benefits_ssp/config/__init__.py
costs_benefits_ssp/config/cb_config.py
costs_benefits_ssp/database/backup/cb_data.db
costs_benefits_ssp/decorators/__init__.py
costs_benefits_ssp/decorators/cb_wrappers.py
costs_benefits_ssp/model/__init__.py
costs_benefits_ssp/model/cb_data_model.py
costs_benefits_ssp/model/cb_update_data_model.py
costs_benefits_ssp/utils/__init__.py
costs_benefits_ssp/utils/utils.py
costs_benefits_ssp-0.1.19.dist-info/licenses/LICENSE
costs_benefits_ssp-0.1.19.dist-info/METADATA
costs_benefits_ssp-0.1.19.dist-info/WHEEL
costs_benefits_ssp-0.1.19.dist-info/top_level.txt
costs_benefits_ssp-0.1.19.dist-info/RECORD
