Metadata-Version: 2.4
Name: costs_benefits_ssp
Version: 0.1.19
Summary: Costs and Benefits package
Home-page: https://github.com/milocortes/costs_benefits_ssp.git
Author: Hermilo Cortés
Author-email: hermilocg@tec.mx
Requires-Python: >=3.11
License-File: LICENSE
Requires-Dist: openpyxl>=3.1.2
Requires-Dist: pandas>=2.2.1
Requires-Dist: sqlalchemy>=2.0.29
Dynamic: author
Dynamic: author-email
Dynamic: home-page
Dynamic: license-file
Dynamic: requires-python
